aggressor.py
aggressor-0.0.1a0.dist-info/METADATA
aggressor-0.0.1a0.dist-info/WHEEL
aggressor-0.0.1a0.dist-info/entry_points.txt
aggressor-0.0.1a0.dist-info/top_level.txt
aggressor-0.0.1a0.dist-info/RECORD
