Metadata-Version: 2.1
Name: aggressor
Version: 0.0.1a0
Summary: Ultra-minimal autoregressive diffusion model for image generation
Home-page: https://github.com/JosefAlbers/Aggressor
Author: Josef Albers
Author-email: albersj66@gmail.com
License: Apache License 2.0
Requires-Python: >=3.12.3
Requires-Dist: datasets ==3.0.0
Requires-Dist: einops ==0.8.0
Requires-Dist: mlx ==0.17.3
Requires-Dist: numpy ==2.1.1
Requires-Dist: pillow ==10.4.0
Requires-Dist: fire ==0.6.0
